mwcommons/__init__.py
mwcommons/exceptions.py
mwcommons/logging_formatter.py
mwcommons/ticdat_types.py
mwcommons/ticdat_utils.py
mwcommons-0.0.3.dist-info/METADATA
mwcommons-0.0.3.dist-info/WHEEL
mwcommons-0.0.3.dist-info/licenses/LICENSE
mwcommons-0.0.3.dist-info/RECORD
