Metadata-Version: 2.4
Name: mwcommons
Version: 0.0.3
Summary: A utility package designed to enhance workflows projects that use ticdat.
Project-URL: homepage, https://github.com/mipwise/mwcommons
Project-URL: source, https://github.com/mipwise/mwcommons
Project-URL: tracker, https://github.com/mipwise/mwcommons/issues
Author-email: Mip Wise <contact@mipwise.com>
License: BSD 2-Clause License
License-File: LICENSE
Requires-Python: <4.0.0,>=3.11.0
Requires-Dist: numpy>=2.0.0
Requires-Dist: pandas>=2.2.3
Requires-Dist: ticdat>=0.2.29
Provides-Extra: dev
Requires-Dist: openpyxl>=3.1.5; extra == 'dev'
Requires-Dist: ruff>=0.9.4; extra == 'dev'
